atomcraft/__init__.py
atomcraft-0.0.0.dist-info/METADATA
atomcraft-0.0.0.dist-info/WHEEL
atomcraft-0.0.0.dist-info/top_level.txt
atomcraft-0.0.0.dist-info/zip-safe
atomcraft-0.0.0.dist-info/RECORD
