Metadata-Version: 2.1
Name: atomcraft
Version: 0.0.0
Summary: atomcraft
Home-page: https://www.lockhartlab.org
Author: C. Lockhart
Author-email: chris@lockhartlab.org
License: UNKNOWN
Platform: UNKNOWN
